{"__format__": 1, "dependencies": {"certifi": {"2019.3.9": []}, "chardet": {"3.0.4": []}, "defusedxml": {"0.5.0": []}, "django": {"2.0.13": ["pytz"]}, "django-allauth": {"0.39.1": ["django>=1.11", "python3-openid>=3.0.8", "requests", "requests-oauthlib>=0.3.0"]}, "idna": {"2.8": []}, "oauthlib": {"3.0.1": []}, "python3-openid": {"3.1.0": ["defusedxml"]}, "pytz": {"2018.9": [], "2019.1": []}, "requests": {"2.21.0": ["certifi>=2017.4.17", "chardet<3.1.0,>=3.0.2", "idna<2.9,>=2.5", "urllib3<1.25,>=1.21.1"]}, "requests-oauthlib": {"1.2.0": ["oauthlib>=3.0.0", "requests>=2.0.0"]}, "urllib3": {"1.24.3": []}}}